unitgen
