Metadata-Version: 2.1
Name: unitgen
Version: 1.2
Summary: Generate unit tests boilerplate code
Home-page: https://github.com/susmitpy/unitgen
Author: Susmit Rajeev Vengurlekar
Author-email: susmit.py@gmail.com
License: GPL
Download-URL: https://github.com/susmitpy/unitgen/archive/refs/tags/v_1.2.tar.gz
Keywords: generate unit tests,generate tests,tests generator,boilerplate generator
Platform: UNKNOWN
Classifier: Development Status :: 5 - Production/Stable 
Classifier: Intended Audience :: Developers
Classifier: Topic :: Software Development :: Build Tools
Classifier: License :: OSI Approved :: GNU General Public License (GPL)
Classifier: Programming Language :: Python :: 3
Classifier: Programming Language :: Python :: 3.4
Classifier: Programming Language :: Python :: 3.5
Classifier: Programming Language :: Python :: 3.6
Classifier: Programming Language :: Python :: 3.7
Classifier: Programming Language :: Python :: 3.8
Classifier: Programming Language :: Python :: 3.9
